imageanalysis/__init__.py
imageanalysis/app.py
imageanalysis/gridding.py
imageanalysis/io.py
imageanalysis/mapping.py
imageanalysis/structures.py
imageanalysis/ui/__init__.py
imageanalysis/ui/main_window.py
imageanalysis/ui/selection_widgets.py
imageanalysis/ui/data_view_widget/__init__.py
imageanalysis/ui/data_view_widget/gridded_image_data_widget.py
imageanalysis/ui/data_view_widget/raw_image_data_widget.py
imageanalysis/ui/data_view_widget/spec_data_widget.py
imageanalysis/ui/data_view_widget/utils.py
imageanalysis/ui/plot_view_widget/__init__.py
image_analysis-0.0.2.dist-info/LICENSE.txt
image_analysis-0.0.2.dist-info/METADATA
image_analysis-0.0.2.dist-info/WHEEL
image_analysis-0.0.2.dist-info/top_level.txt
image_analysis-0.0.2.dist-info/RECORD
