Metadata-Version: 2.1
Name: image-analysis
Version: 0.0.2
Summary: Python-based software for XRD data analysis.
Home-page: https://github.com/henryjsmith12/image-analysis
Author: Henry Smith
Author-email: smithh@anl.gov
License: UNKNOWN
Keywords: python,pyqtgraph,image-analysis,xrd
Platform: UNKNOWN
